xtalpi/__init__.py
xtalpi/cli.py
xtalpi/xtalpi.py
xtalpi-0.0.1.dist-info/AUTHORS.rst
xtalpi-0.0.1.dist-info/METADATA
xtalpi-0.0.1.dist-info/WHEEL
xtalpi-0.0.1.dist-info/entry_points.txt
xtalpi-0.0.1.dist-info/top_level.txt
xtalpi-0.0.1.dist-info/RECORD
