Metadata-Version: 2.1
Name: xtalpi
Version: 0.0.1
Summary: xtalpi
Home-page: https://github.com/taceywong/xtalpi
Author: Tacey Wong
Author-email: xinyong.wang@xtalpi.com
License: UNKNOWN
Keywords: xtalpi
Platform: UNKNOWN
Classifier: Development Status :: 2 - Pre-Alpha
Classifier: Intended Audience :: Developers
Classifier: Natural Language :: English
Classifier: Programming Language :: Python :: 3
Classifier: Programming Language :: Python :: 3.5
Classifier: Programming Language :: Python :: 3.6
Classifier: Programming Language :: Python :: 3.7
Classifier: Programming Language :: Python :: 3.8
Requires-Python: >=3.5
Requires-Dist: Click (>=7.0)
